[
    {
        "args": "spmv.py --l2-stream-dd 100 --l2-stream-dd-ovr 0 --disable-l1-nlp --disable-l2-amp --disable-llc-stream -1gb -pd=0 --matrix-format csr benchmark --repetitions 10 SuiteSparse GAP-web",
        "time": "2025-03-05 23:59:41.235454",
        "host": "dune",
        "git-hash": "002ef11da73c4f8a09efa5170b007d612b8752cf",
        "status": "complete",
        "exec_times_ns": [
            3385244000,
            3377440000,
            3377238000,
            3409695000,
            3409785000,
            3374882000,
            3381548000,
            3385690000,
            3386314000,
            3377282000
        ],
        "filtered": [
            3385244000,
            3377440000,
            3377238000,
            3409695000,
            3409785000,
            3374882000,
            3381548000,
            3385690000,
            3386314000,
            3377282000
        ],
        "mean_ms": 3386.512,
        "std_dev": 12.888,
        "cv": 0.004
    },
    {
        "args": "spmv.py --l2-stream-dd 100 --l2-stream-dd-ovr 0 --disable-l1-nlp --disable-l2-amp --disable-llc-stream -1gb -pd=4 --matrix-format csr benchmark --repetitions 10 SuiteSparse GAP-web",
        "time": "2025-03-06 00:01:18.041219",
        "host": "dune",
        "git-hash": "002ef11da73c4f8a09efa5170b007d612b8752cf",
        "status": "complete",
        "exec_times_ns": [
            4294558999,
            4297947000,
            4292599000,
            4300026000,
            4292904000,
            4288456000,
            4307085000,
            4303205000,
            4302281000,
            4299181000
        ],
        "filtered": [
            4294558999,
            4297947000,
            4292599000,
            4300026000,
            4292904000,
            4288456000,
            4307085000,
            4303205000,
            4302281000,
            4299181000
        ],
        "mean_ms": 4297.824,
        "std_dev": 5.688,
        "cv": 0.001
    },
    {
        "args": "spmv.py --l2-stream-dd 100 --l2-stream-dd-ovr 0 --disable-l1-nlp --disable-l2-amp --disable-llc-stream -1gb -pd=8 --matrix-format csr benchmark --repetitions 10 SuiteSparse GAP-web",
        "time": "2025-03-06 00:03:03.584239",
        "host": "dune",
        "git-hash": "002ef11da73c4f8a09efa5170b007d612b8752cf",
        "status": "complete",
        "exec_times_ns": [
            4199881999,
            4211973000,
            4208642000,
            4196176999,
            4192141999,
            4194902000,
            4205903000,
            4198216000,
            4194174000,
            4196564000
        ],
        "filtered": [
            4199881999,
            4211973000,
            4208642000,
            4196176999,
            4192141999,
            4194902000,
            4205903000,
            4198216000,
            4194174000,
            4196564000
        ],
        "mean_ms": 4199.857,
        "std_dev": 6.7,
        "cv": 0.002
    },
    {
        "args": "spmv.py --l2-stream-dd 100 --l2-stream-dd-ovr 0 --disable-l1-nlp --disable-l2-amp --disable-llc-stream -1gb -pd=12 --matrix-format csr benchmark --repetitions 10 SuiteSparse GAP-web",
        "time": "2025-03-06 00:04:48.553352",
        "host": "dune",
        "git-hash": "002ef11da73c4f8a09efa5170b007d612b8752cf",
        "status": "complete",
        "exec_times_ns": [
            4180212000,
            4176783000,
            4166945000,
            4182565999,
            4183370000,
            4176354000,
            4179785000,
            4181707000,
            4181967000,
            4182056000
        ],
        "filtered": [
            4180212000,
            4176783000,
            4166945000,
            4182565999,
            4183370000,
            4176354000,
            4179785000,
            4181707000,
            4181967000,
            4182056000
        ],
        "mean_ms": 4179.174,
        "std_dev": 4.902,
        "cv": 0.001
    },
    {
        "args": "spmv.py --l2-stream-dd 100 --l2-stream-dd-ovr 0 --disable-l1-nlp --disable-l2-amp --disable-llc-stream -1gb -pd=16 --matrix-format csr benchmark --repetitions 10 SuiteSparse GAP-web",
        "time": "2025-03-06 00:06:32.994389",
        "host": "dune",
        "git-hash": "002ef11da73c4f8a09efa5170b007d612b8752cf",
        "status": "complete",
        "exec_times_ns": [
            4158607000,
            4163458999,
            4164677000,
            4164531000,
            4167409000,
            4164385000,
            4164677000,
            4164312000,
            4163861000,
            4163443000
        ],
        "filtered": [
            4158607000,
            4163458999,
            4164677000,
            4164531000,
            4167409000,
            4164385000,
            4164677000,
            4164312000,
            4163861000,
            4163443000
        ],
        "mean_ms": 4163.936,
        "std_dev": 2.179,
        "cv": 0.001
    },
    {
        "args": "spmv.py --l2-stream-dd 100 --l2-stream-dd-ovr 0 --disable-l1-nlp --disable-l2-amp --disable-llc-stream -1gb -pd=20 --matrix-format csr benchmark --repetitions 10 SuiteSparse GAP-web",
        "time": "2025-03-06 00:08:17.053450",
        "host": "dune",
        "git-hash": "002ef11da73c4f8a09efa5170b007d612b8752cf",
        "status": "complete",
        "exec_times_ns": [
            4161609999,
            4157644000,
            4156056999,
            4149344000,
            4152957000,
            4161772000,
            4157187999,
            4160595000,
            4154097000,
            4158941000
        ],
        "filtered": [
            4161609999,
            4157644000,
            4156056999,
            4149344000,
            4152957000,
            4161772000,
            4157187999,
            4160595000,
            4154097000,
            4158941000
        ],
        "mean_ms": 4157.02,
        "std_dev": 4.02,
        "cv": 0.001
    },
    {
        "args": "spmv.py --l2-stream-dd 100 --l2-stream-dd-ovr 0 --disable-l1-nlp --disable-l2-amp --disable-llc-stream -1gb -pd=24 --matrix-format csr benchmark --repetitions 10 SuiteSparse GAP-web",
        "time": "2025-03-06 00:10:01.156157",
        "host": "dune",
        "git-hash": "002ef11da73c4f8a09efa5170b007d612b8752cf",
        "status": "complete",
        "exec_times_ns": [
            4194250000,
            4191503000,
            4204961000,
            4204568000,
            4200332999,
            4192616000,
            4204478000,
            4189821000,
            4198882000,
            4205662000
        ],
        "filtered": [
            4194250000,
            4191503000,
            4204961000,
            4204568000,
            4200332999,
            4192616000,
            4204478000,
            4189821000,
            4198882000,
            4205662000
        ],
        "mean_ms": 4198.707,
        "std_dev": 6.197,
        "cv": 0.001
    },
    {
        "args": "spmv.py --l2-stream-dd 100 --l2-stream-dd-ovr 0 --disable-l1-nlp --disable-l2-amp --disable-llc-stream -1gb -pd=28 --matrix-format csr benchmark --repetitions 10 SuiteSparse GAP-web",
        "time": "2025-03-06 00:11:45.908867",
        "host": "dune",
        "git-hash": "002ef11da73c4f8a09efa5170b007d612b8752cf",
        "status": "complete",
        "exec_times_ns": [
            4133918999,
            4132144000,
            4129634000,
            4117441000,
            4131928000,
            4130464000,
            4120511999,
            4118842000,
            4131655000,
            4118090999
        ],
        "filtered": [
            4133918999,
            4132144000,
            4129634000,
            4117441000,
            4131928000,
            4130464000,
            4120511999,
            4118842000,
            4131655000,
            4118090999
        ],
        "mean_ms": 4126.463,
        "std_dev": 6.797,
        "cv": 0.002
    },
    {
        "args": "spmv.py --l2-stream-dd 100 --l2-stream-dd-ovr 0 --disable-l1-nlp --disable-l2-amp --disable-llc-stream -1gb -pd=32 --matrix-format csr benchmark --repetitions 10 SuiteSparse GAP-web",
        "time": "2025-03-06 00:13:29.856229",
        "host": "dune",
        "git-hash": "002ef11da73c4f8a09efa5170b007d612b8752cf",
        "status": "complete",
        "exec_times_ns": [
            4112406000,
            4126859999,
            4113392000,
            4125278000,
            4123748000,
            4116360000,
            4116512000,
            4126102000,
            4119449000,
            4123656999
        ],
        "filtered": [
            4112406000,
            4126859999,
            4113392000,
            4125278000,
            4123748000,
            4116360000,
            4116512000,
            4126102000,
            4119449000,
            4123656999
        ],
        "mean_ms": 4120.376,
        "std_dev": 5.428,
        "cv": 0.001
    },
    {
        "args": "spmv.py --l2-stream-dd 100 --l2-stream-dd-ovr 0 --disable-l1-nlp --disable-l2-amp --disable-llc-stream -1gb -pd=36 --matrix-format csr benchmark --repetitions 10 SuiteSparse GAP-web",
        "time": "2025-03-06 00:15:13.469470",
        "host": "dune",
        "git-hash": "002ef11da73c4f8a09efa5170b007d612b8752cf",
        "status": "complete",
        "exec_times_ns": [
            4114760999,
            4100374999,
            4115980000,
            4105239000,
            4099637999,
            4116231000,
            4099230999,
            4102340000,
            4116920000,
            4113006999
        ],
        "filtered": [
            4114760999,
            4100374999,
            4115980000,
            4105239000,
            4099637999,
            4116231000,
            4099230999,
            4102340000,
            4116920000,
            4113006999
        ],
        "mean_ms": 4108.372,
        "std_dev": 7.638,
        "cv": 0.002
    },
    {
        "args": "spmv.py --l2-stream-dd 100 --l2-stream-dd-ovr 0 --disable-l1-nlp --disable-l2-amp --disable-llc-stream -1gb -pd=40 --matrix-format csr benchmark --repetitions 10 SuiteSparse GAP-web",
        "time": "2025-03-06 00:16:57.249058",
        "host": "dune",
        "git-hash": "002ef11da73c4f8a09efa5170b007d612b8752cf",
        "status": "complete",
        "exec_times_ns": [
            4138352000,
            4139827000,
            4139058999,
            4143462999,
            4131959000,
            4146542000,
            4142532000,
            4131906000,
            4144002000,
            4134153000
        ],
        "filtered": [
            4138352000,
            4139827000,
            4139058999,
            4143462999,
            4131959000,
            4146542000,
            4142532000,
            4131906000,
            4144002000,
            4134153000
        ],
        "mean_ms": 4139.179,
        "std_dev": 5.148,
        "cv": 0.001
    },
    {
        "args": "spmv.py --l2-stream-dd 100 --l2-stream-dd-ovr 0 --disable-l1-nlp --disable-l2-amp --disable-llc-stream -1gb -pd=44 --matrix-format csr benchmark --repetitions 10 SuiteSparse GAP-web",
        "time": "2025-03-06 00:18:41.151268",
        "host": "dune",
        "git-hash": "002ef11da73c4f8a09efa5170b007d612b8752cf",
        "status": "complete",
        "exec_times_ns": [
            4125452000,
            4130266000,
            4132392000,
            4132306000,
            4137889999,
            4141626999,
            4136730000,
            4128827000,
            4124232000,
            4127938999
        ],
        "filtered": [
            4125452000,
            4130266000,
            4132392000,
            4132306000,
            4137889999,
            4141626999,
            4136730000,
            4128827000,
            4124232000,
            4127938999
        ],
        "mean_ms": 4131.766,
        "std_dev": 5.6,
        "cv": 0.001
    },
    {
        "args": "spmv.py --l2-stream-dd 100 --l2-stream-dd-ovr 0 --disable-l1-nlp --disable-l2-amp --disable-llc-stream -1gb -pd=48 --matrix-format csr benchmark --repetitions 10 SuiteSparse GAP-web",
        "time": "2025-03-06 00:20:25.141286",
        "host": "dune",
        "git-hash": "002ef11da73c4f8a09efa5170b007d612b8752cf",
        "status": "complete",
        "exec_times_ns": [
            4135932999,
            4133254000,
            4125020000,
            4140949000,
            4132564999,
            4132393000,
            4122027000,
            4135715000,
            4137505000,
            4135795000
        ],
        "filtered": [
            4135932999,
            4133254000,
            4125020000,
            4140949000,
            4132564999,
            4132393000,
            4122027000,
            4135715000,
            4137505000,
            4135795000
        ],
        "mean_ms": 4133.116,
        "std_dev": 5.694,
        "cv": 0.001
    },
    {
        "args": "spmv.py --l2-stream-dd 100 --l2-stream-dd-ovr 0 --disable-l1-nlp --disable-l2-amp --disable-llc-stream -1gb -pd=52 --matrix-format csr benchmark --repetitions 10 SuiteSparse GAP-web",
        "time": "2025-03-06 00:22:08.826867",
        "host": "dune",
        "git-hash": "002ef11da73c4f8a09efa5170b007d612b8752cf",
        "status": "complete",
        "exec_times_ns": [
            4093845000,
            4080400000,
            4079556000,
            4074976999,
            4076656000,
            4092670000,
            4095447000,
            4077326000,
            4081125000,
            4086812000
        ],
        "filtered": [
            4093845000,
            4080400000,
            4079556000,
            4074976999,
            4076656000,
            4092670000,
            4095447000,
            4077326000,
            4081125000,
            4086812000
        ],
        "mean_ms": 4083.881,
        "std_dev": 7.687,
        "cv": 0.002
    },
    {
        "args": "spmv.py --l2-stream-dd 100 --l2-stream-dd-ovr 0 --disable-l1-nlp --disable-l2-amp --disable-llc-stream -1gb -pd=56 --matrix-format csr benchmark --repetitions 10 SuiteSparse GAP-web",
        "time": "2025-03-06 00:23:52.194967",
        "host": "dune",
        "git-hash": "002ef11da73c4f8a09efa5170b007d612b8752cf",
        "status": "complete",
        "exec_times_ns": [
            4120967000,
            4129758000,
            4130569999,
            4138698000,
            4127719000,
            4120083000,
            4136132000,
            4119465000,
            4121641999,
            4131686000
        ],
        "filtered": [
            4120967000,
            4129758000,
            4130569999,
            4138698000,
            4127719000,
            4120083000,
            4136132000,
            4119465000,
            4121641999,
            4131686000
        ],
        "mean_ms": 4127.672,
        "std_dev": 6.898,
        "cv": 0.002
    },
    {
        "args": "spmv.py --l2-stream-dd 100 --l2-stream-dd-ovr 0 --disable-l1-nlp --disable-l2-amp --disable-llc-stream -1gb -pd=60 --matrix-format csr benchmark --repetitions 10 SuiteSparse GAP-web",
        "time": "2025-03-06 00:25:36.139062",
        "host": "dune",
        "git-hash": "002ef11da73c4f8a09efa5170b007d612b8752cf",
        "status": "complete",
        "exec_times_ns": [
            4096513000,
            4098236000,
            4077332000,
            4091039000,
            4090922000,
            4088902000,
            4087598000,
            4091668000,
            4097346000,
            4090999000
        ],
        "filtered": [
            4096513000,
            4098236000,
            4077332000,
            4091039000,
            4090922000,
            4088902000,
            4087598000,
            4091668000,
            4097346000,
            4090999000
        ],
        "mean_ms": 4091.055,
        "std_dev": 6.021,
        "cv": 0.001
    },
    {
        "args": "spmv.py --l2-stream-dd 100 --l2-stream-dd-ovr 0 --disable-l1-nlp --disable-l2-amp --disable-llc-stream -1gb -pd=64 --matrix-format csr benchmark --repetitions 10 SuiteSparse GAP-web",
        "time": "2025-03-06 00:27:19.511249",
        "host": "dune",
        "git-hash": "002ef11da73c4f8a09efa5170b007d612b8752cf",
        "status": "complete",
        "exec_times_ns": [
            4096066000,
            4090470000,
            4083249999,
            4098786999,
            4097941999,
            4079841000,
            4096825000,
            4094856000,
            4096624000,
            4078883000
        ],
        "filtered": [
            4096066000,
            4090470000,
            4083249999,
            4098786999,
            4097941999,
            4079841000,
            4096825000,
            4094856000,
            4096624000,
            4078883000
        ],
        "mean_ms": 4091.354,
        "std_dev": 7.784,
        "cv": 0.002
    },
    {
        "args": "spmv.py --l2-stream-dd 100 --l2-stream-dd-ovr 0 --disable-l1-nlp --disable-l2-amp --disable-llc-stream -1gb -pd=68 --matrix-format csr benchmark --repetitions 10 SuiteSparse GAP-web",
        "time": "2025-03-06 00:29:02.840898",
        "host": "dune",
        "git-hash": "002ef11da73c4f8a09efa5170b007d612b8752cf",
        "status": "complete",
        "exec_times_ns": [
            4088510999,
            4090505000,
            4090449999,
            4093777000,
            4088276999,
            4095144000,
            4080221000,
            4089928999,
            4076275000,
            4077522000
        ],
        "filtered": [
            4088510999,
            4090505000,
            4090449999,
            4093777000,
            4088276999,
            4095144000,
            4080221000,
            4089928999,
            4076275000,
            4077522000
        ],
        "mean_ms": 4087.061,
        "std_dev": 6.664,
        "cv": 0.002
    },
    {
        "args": "spmv.py --l2-stream-dd 100 --l2-stream-dd-ovr 0 --disable-l1-nlp --disable-l2-amp --disable-llc-stream -1gb -pd=72 --matrix-format csr benchmark --repetitions 10 SuiteSparse GAP-web",
        "time": "2025-03-06 00:30:46.268839",
        "host": "dune",
        "git-hash": "002ef11da73c4f8a09efa5170b007d612b8752cf",
        "status": "complete",
        "exec_times_ns": [
            4096771999,
            4089263000,
            4095987000,
            4087821000,
            4096665000,
            4096682000,
            4096676000,
            4085052000,
            4095015000,
            4093141000
        ],
        "filtered": [
            4096771999,
            4089263000,
            4095987000,
            4087821000,
            4096665000,
            4096682000,
            4096676000,
            4085052000,
            4095015000,
            4093141000
        ],
        "mean_ms": 4093.307,
        "std_dev": 4.356,
        "cv": 0.001
    },
    {
        "args": "spmv.py --l2-stream-dd 100 --l2-stream-dd-ovr 0 --disable-l1-nlp --disable-l2-amp --disable-llc-stream -1gb -pd=76 --matrix-format csr benchmark --repetitions 10 SuiteSparse GAP-web",
        "time": "2025-03-06 00:32:29.506481",
        "host": "dune",
        "git-hash": "002ef11da73c4f8a09efa5170b007d612b8752cf",
        "status": "complete",
        "exec_times_ns": [
            4096375000,
            4091029000,
            4083191000,
            4088574000,
            4093043000,
            4092546999,
            4093756000,
            4097175000,
            4076921999,
            4092322000
        ],
        "filtered": [
            4096375000,
            4091029000,
            4083191000,
            4088574000,
            4093043000,
            4092546999,
            4093756000,
            4097175000,
            4076921999,
            4092322000
        ],
        "mean_ms": 4090.493,
        "std_dev": 6.195,
        "cv": 0.002
    },
    {
        "args": "spmv.py --l2-stream-dd 100 --l2-stream-dd-ovr 0 --disable-l1-nlp --disable-l2-amp --disable-llc-stream -1gb -pd=80 --matrix-format csr benchmark --repetitions 10 SuiteSparse GAP-web",
        "time": "2025-03-06 00:34:12.806640",
        "host": "dune",
        "git-hash": "002ef11da73c4f8a09efa5170b007d612b8752cf",
        "status": "complete",
        "exec_times_ns": [
            4084677000,
            4092803000,
            4097868000,
            4090518000,
            4092082000,
            4094438000,
            4086900000,
            4097092000,
            4098911000,
            4099139000
        ],
        "filtered": [
            4084677000,
            4092803000,
            4097868000,
            4090518000,
            4092082000,
            4094438000,
            4086900000,
            4097092000,
            4098911000,
            4099139000
        ],
        "mean_ms": 4093.443,
        "std_dev": 5.019,
        "cv": 0.001
    },
    {
        "args": "spmv.py --l2-stream-dd 100 --l2-stream-dd-ovr 0 --disable-l1-nlp --disable-l2-amp --disable-llc-stream -1gb -pd=84 --matrix-format csr benchmark --repetitions 10 SuiteSparse GAP-web",
        "time": "2025-03-06 00:35:56.466781",
        "host": "dune",
        "git-hash": "002ef11da73c4f8a09efa5170b007d612b8752cf",
        "status": "complete",
        "exec_times_ns": [
            4094087000,
            4086158000,
            4095274000,
            4092835000,
            4090294000,
            4094988000,
            4091715000,
            4093812000,
            4081392000,
            4093223000
        ],
        "filtered": [
            4094087000,
            4086158000,
            4095274000,
            4092835000,
            4090294000,
            4094988000,
            4091715000,
            4093812000,
            4081392000,
            4093223000
        ],
        "mean_ms": 4091.378,
        "std_dev": 4.413,
        "cv": 0.001
    },
    {
        "args": "spmv.py --l2-stream-dd 100 --l2-stream-dd-ovr 0 --disable-l1-nlp --disable-l2-amp --disable-llc-stream -1gb -pd=88 --matrix-format csr benchmark --repetitions 10 SuiteSparse GAP-web",
        "time": "2025-03-06 00:37:40.066045",
        "host": "dune",
        "git-hash": "002ef11da73c4f8a09efa5170b007d612b8752cf",
        "status": "complete",
        "exec_times_ns": [
            4093488000,
            4084454000,
            4084262000,
            4094048000,
            4090883000,
            4098449999,
            4099548000,
            4093000000,
            4100189000,
            4087001000
        ],
        "filtered": [
            4093488000,
            4084454000,
            4084262000,
            4094048000,
            4090883000,
            4098449999,
            4099548000,
            4093000000,
            4100189000,
            4087001000
        ],
        "mean_ms": 4092.532,
        "std_dev": 5.9,
        "cv": 0.001
    },
    {
        "args": "spmv.py --l2-stream-dd 100 --l2-stream-dd-ovr 0 --disable-l1-nlp --disable-l2-amp --disable-llc-stream -1gb -pd=92 --matrix-format csr benchmark --repetitions 10 SuiteSparse GAP-web",
        "time": "2025-03-06 00:39:23.537565",
        "host": "dune",
        "git-hash": "002ef11da73c4f8a09efa5170b007d612b8752cf",
        "status": "complete",
        "exec_times_ns": [
            4086318000,
            4092386000,
            4074486000,
            4077082000,
            4081302000,
            4087701000,
            4088681000,
            4082026000,
            4091231999,
            4080498999
        ],
        "filtered": [
            4086318000,
            4092386000,
            4074486000,
            4077082000,
            4081302000,
            4087701000,
            4088681000,
            4082026000,
            4091231999,
            4080498999
        ],
        "mean_ms": 4084.171,
        "std_dev": 6.01,
        "cv": 0.001
    },
    {
        "args": "spmv.py --l2-stream-dd 100 --l2-stream-dd-ovr 0 --disable-l1-nlp --disable-l2-amp --disable-llc-stream -1gb -pd=96 --matrix-format csr benchmark --repetitions 10 SuiteSparse GAP-web",
        "time": "2025-03-06 00:41:07.064546",
        "host": "dune",
        "git-hash": "002ef11da73c4f8a09efa5170b007d612b8752cf",
        "status": "complete",
        "exec_times_ns": [
            4080488000,
            4082095000,
            4079875999,
            4095669000,
            4080669000,
            4093522000,
            4097526000,
            4080687000,
            4094500000,
            4093020000
        ],
        "filtered": [
            4080488000,
            4082095000,
            4079875999,
            4095669000,
            4080669000,
            4093522000,
            4097526000,
            4080687000,
            4094500000,
            4093020000
        ],
        "mean_ms": 4087.805,
        "std_dev": 7.54,
        "cv": 0.002
    },
    {
        "args": "spmv.py --l2-stream-dd 100 --l2-stream-dd-ovr 0 --disable-l1-nlp --disable-l2-amp --disable-llc-stream -1gb -pd=100 --matrix-format csr benchmark --repetitions 10 SuiteSparse GAP-web",
        "time": "2025-03-06 00:42:50.415828",
        "host": "dune",
        "git-hash": "002ef11da73c4f8a09efa5170b007d612b8752cf",
        "status": "complete",
        "exec_times_ns": [
            4086999999,
            4095625000,
            4078281999,
            4076641999,
            4087150000,
            4092035000,
            4095282000,
            4091607000,
            4076543000,
            4090556000
        ],
        "filtered": [
            4086999999,
            4095625000,
            4078281999,
            4076641999,
            4087150000,
            4092035000,
            4095282000,
            4091607000,
            4076543000,
            4090556000
        ],
        "mean_ms": 4087.072,
        "std_dev": 7.415,
        "cv": 0.002
    },
    {
        "args": "spmv.py --l2-stream-dd 100 --l2-stream-dd-ovr 0 --disable-l1-nlp --disable-l2-amp --disable-llc-stream -1gb -pd=104 --matrix-format csr benchmark --repetitions 10 SuiteSparse GAP-web",
        "time": "2025-03-06 00:44:33.856130",
        "host": "dune",
        "git-hash": "002ef11da73c4f8a09efa5170b007d612b8752cf",
        "status": "complete",
        "exec_times_ns": [
            4094604000,
            4092018000,
            4078478999,
            4082104000,
            4091535000,
            4097031999,
            4089475000,
            4096285000,
            4097168000,
            4092993000
        ],
        "filtered": [
            4094604000,
            4092018000,
            4078478999,
            4082104000,
            4091535000,
            4097031999,
            4089475000,
            4096285000,
            4097168000,
            4092993000
        ],
        "mean_ms": 4091.169,
        "std_dev": 6.312,
        "cv": 0.002
    },
    {
        "args": "spmv.py --l2-stream-dd 100 --l2-stream-dd-ovr 0 --disable-l1-nlp --disable-l2-amp --disable-llc-stream -1gb -pd=108 --matrix-format csr benchmark --repetitions 10 SuiteSparse GAP-web",
        "time": "2025-03-06 00:46:17.321017",
        "host": "dune",
        "git-hash": "002ef11da73c4f8a09efa5170b007d612b8752cf",
        "status": "complete",
        "exec_times_ns": [
            4090086000,
            4076372000,
            4091808000,
            4088215000,
            4091332999,
            4077918000,
            4082659999,
            4081170000,
            4091338000,
            4091258000
        ],
        "filtered": [
            4090086000,
            4076372000,
            4091808000,
            4088215000,
            4091332999,
            4077918000,
            4082659999,
            4081170000,
            4091338000,
            4091258000
        ],
        "mean_ms": 4086.216,
        "std_dev": 6.073,
        "cv": 0.001
    },
    {
        "args": "spmv.py --l2-stream-dd 100 --l2-stream-dd-ovr 0 --disable-l1-nlp --disable-l2-amp --disable-llc-stream -1gb -pd=112 --matrix-format csr benchmark --repetitions 10 SuiteSparse GAP-web",
        "time": "2025-03-06 00:48:00.775461",
        "host": "dune",
        "git-hash": "002ef11da73c4f8a09efa5170b007d612b8752cf",
        "status": "complete",
        "exec_times_ns": [
            4098636000,
            4081842000,
            4081598999,
            4103055000,
            4102960000,
            4082697999,
            4096584000,
            4085135000,
            4085922000,
            4082703000
        ],
        "filtered": [
            4098636000,
            4081842000,
            4081598999,
            4103055000,
            4102960000,
            4082697999,
            4096584000,
            4085135000,
            4085922000,
            4082703000
        ],
        "mean_ms": 4090.113,
        "std_dev": 9.069,
        "cv": 0.002
    },
    {
        "args": "spmv.py --l2-stream-dd 100 --l2-stream-dd-ovr 0 --disable-l1-nlp --disable-l2-amp --disable-llc-stream -1gb -pd=116 --matrix-format csr benchmark --repetitions 10 SuiteSparse GAP-web",
        "time": "2025-03-06 00:49:44.409567",
        "host": "dune",
        "git-hash": "002ef11da73c4f8a09efa5170b007d612b8752cf",
        "status": "complete",
        "exec_times_ns": [
            4120057000,
            4112275999,
            4108865000,
            4109810000,
            4110843000,
            4112517999,
            4112050000,
            4123426000,
            4118314000,
            4122843999
        ],
        "filtered": [
            4120057000,
            4112275999,
            4108865000,
            4109810000,
            4110843000,
            4112517999,
            4112050000,
            4123426000,
            4118314000,
            4122843999
        ],
        "mean_ms": 4115.1,
        "std_dev": 5.509,
        "cv": 0.001
    },
    {
        "args": "spmv.py --l2-stream-dd 100 --l2-stream-dd-ovr 0 --disable-l1-nlp --disable-l2-amp --disable-llc-stream -1gb -pd=120 --matrix-format csr benchmark --repetitions 10 SuiteSparse GAP-web",
        "time": "2025-03-06 00:51:28.077994",
        "host": "dune",
        "git-hash": "002ef11da73c4f8a09efa5170b007d612b8752cf",
        "status": "complete",
        "exec_times_ns": [
            4078336000,
            4091506000,
            4084240999,
            4093868999,
            4091771999,
            4092334000,
            4081715000,
            4086877000,
            4078365000,
            4094356000
        ],
        "filtered": [
            4078336000,
            4091506000,
            4084240999,
            4093868999,
            4091771999,
            4092334000,
            4081715000,
            4086877000,
            4078365000,
            4094356000
        ],
        "mean_ms": 4087.337,
        "std_dev": 6.297,
        "cv": 0.002
    },
    {
        "args": "spmv.py --l2-stream-dd 100 --l2-stream-dd-ovr 0 --disable-l1-nlp --disable-l2-amp --disable-llc-stream -1gb -pd=124 --matrix-format csr benchmark --repetitions 10 SuiteSparse GAP-web",
        "time": "2025-03-06 00:53:11.912228",
        "host": "dune",
        "git-hash": "002ef11da73c4f8a09efa5170b007d612b8752cf",
        "status": "complete",
        "exec_times_ns": [
            4083712000,
            4090217000,
            4085592000,
            4081858000,
            4088636000,
            4086939000,
            4073805000,
            4071335999,
            4071631000,
            4071467000
        ],
        "filtered": [
            4083712000,
            4090217000,
            4085592000,
            4081858000,
            4088636000,
            4086939000,
            4073805000,
            4071335999,
            4071631000,
            4071467000
        ],
        "mean_ms": 4080.519,
        "std_dev": 7.668,
        "cv": 0.002
    },
    {
        "args": "spmv.py --l2-stream-dd 100 --l2-stream-dd-ovr 0 --disable-l1-nlp --disable-l2-amp --disable-llc-stream -1gb -pd=128 --matrix-format csr benchmark --repetitions 10 SuiteSparse GAP-web",
        "time": "2025-03-06 00:54:55.232789",
        "host": "dune",
        "git-hash": "002ef11da73c4f8a09efa5170b007d612b8752cf",
        "status": "complete",
        "exec_times_ns": [
            4082462999,
            4081976000,
            4078102999,
            4092367999,
            4079687000,
            4091464000,
            4090296999,
            4079106000,
            4086427999,
            4078540000
        ],
        "filtered": [
            4082462999,
            4081976000,
            4078102999,
            4092367999,
            4079687000,
            4091464000,
            4090296999,
            4079106000,
            4086427999,
            4078540000
        ],
        "mean_ms": 4084.043,
        "std_dev": 5.626,
        "cv": 0.001
    }
]